jittok/__init__.py
jittok/__main__.py
jittok/_version.py
jittok/cli.py
jittok/core.py
jittok/exceptions.py
jittok/py.typed
jittok/blob/__init__.py
jittok/blob/core.py
jittok/jpaddress/__init__.py
jittok/jpaddress/core.py
jittok/jpaddress/exceptions.py
jittok/jpdatetime/__init__.py
jittok/jpdatetime/core.py
jittok/jptext/__init__.py
jittok/jptext/cli.py
jittok/jptext/core.py
jittok/jptext/exceptions.py
jittok-0.0.6.dist-info/LICENSE
jittok-0.0.6.dist-info/WHEEL
jittok-0.0.6.dist-info/METADATA
jittok-0.0.6.dist-info/RECORD
