Metadata-Version: 2.1
Name: jittok
Version: 0.0.6
Summary: Swiss Army Knife-like toolbox for data processing
Author-email: osoken <osoken.devel@outlook.jp>
Requires-Dist: regex
Requires-Dist: pykakasi
Requires-Dist: dataclasses; python_version < '3.7'
Requires-Dist: flake8 ; extra == "dev"
Requires-Dist: pytest ; extra == "dev"
Requires-Dist: black ; extra == "dev"
Requires-Dist: mypy ; extra == "dev"
Requires-Dist: tox ; extra == "dev"
Requires-Dist: isort ; extra == "dev"
Requires-Dist: types-regex ; extra == "dev"
Requires-Dist: pytest-mock ; extra == "dev"
Requires-Dist: types-dataclasses ; extra == "dev"
Project-URL: repository, https://github.com/osoken/jittok
Provides-Extra: dev
